apple_style_ui/__init__.py
apple_style_ui/apple_style_ui.py
apple_style_ui-0.1.1.dist-info/METADATA
apple_style_ui-0.1.1.dist-info/WHEEL
apple_style_ui-0.1.1.dist-info/top_level.txt
apple_style_ui-0.1.1.dist-info/RECORD
