Metadata-Version: 2.4
Name: apple-style-ui
Version: 0.1.1
Summary: A library of Apple-style UI components for PyQt6.
Home-page: https://github.com/yamamoto-atsushi/AppleUI.git
Author: Yamamoto Atsushi
Author-email: nasebanaru1975@gmail.com
Classifier: Programming Language :: Python :: 3
Classifier: License :: OSI Approved :: MIT License
Classifier: Operating System :: OS Independent
Requires-Python: >=3.7
Requires-Dist: PyQt6>=6.0
Dynamic: author
Dynamic: author-email
Dynamic: classifier
Dynamic: description
Dynamic: description-content-type
Dynamic: home-page
Dynamic: requires-dist
Dynamic: requires-python
Dynamic: summary
